Group09_Lab05_Part4/complement.v
/*
    * CO224 - Computer Architecture
    * Lab 05 - Part 3
    * 2's Complement Unit
    * Group 09 (E/20/148, E/20/157)
    * 2024-04-24
    * Version 1.0
*/


// This module is used to produce 2's complement value of a given 8 bit data set
module complement(DATA2, RESULT);
    // Input-output Declaration
    input [7:0] DATA2;
    output [7:0] RESULT;

    // Result
    assign #1 RESULT = ~DATA2 + 8'b0000_0001;

    /*initial begin
        $monitor("DATA=%b,  RESULT=%b\n", DATA2, RESULT);
    end*/

endmodule

Group09_Lab05_Part4/mux.v
/*
    * CO224 - Computer Architecture
    * Lab 05 - Part 3
    * Multiplexer unit
    * Group 09 (E/20/148, E/20/157)
    * 2024-04-24
    * Version 1.0
*/

module mux(IN1, IN2, SELECT, OUT);
    // Input-output Declaration
    input[7:0] IN1, IN2;
    input SELECT;

    output reg[7:0] OUT;

    // Operation
    always @ (IN1, IN2, SELECT)
    begin
      if(SELECT == 0) begin
        OUT = IN1;
      end

      else if(SELECT == 1) begin
        OUT = IN2;
      end

     //$display("IN1: %b \t IN2: %b \t S: %b \t OUT: %b", IN1, IN2, SELECT, OUT);
    end

endmodule

Group09_Lab05_Part3/reg_file.v
/*
    * CO224 - Computer Architecture
    * Lab 05 - Part 3
    * reg_file module
    * Group 09 (E/20/148, E/20/157)
    * 2024-04-24
    * Version 1.0
*/

module reg_file(IN, OUT1, OUT2, INADDRESS, OUT1ADDRESS, OUT2ADDRESS, WRITE, CLK, RESET);
    // Port declaration
    input [7:0] IN; // Data input for writing
    input [2:0] INADDRESS; 
    input [2:0] OUT1ADDRESS, OUT2ADDRESS; // Data addresses


    input CLK, RESET, WRITE; // Control signals

    output reg [7:0] OUT1, OUT2; // Data outputs

    // Register Allocation
    reg [7:0] REGISTER [7:0]; // 8 x 8 register block

    // variable for counting
    integer i;

    // Asynchronous Data Operations (READ)
    always @ (OUT1ADDRESS, OUT2ADDRESS)
    begin
      //if (WRITE == 1'b0) begin
        #2   // Artificial delay of 2 time units
        OUT1 = REGISTER[OUT1ADDRESS];
        OUT2 = REGISTER[OUT2ADDRESS];
        //$display("READ DATA:: \tREG[%d]: %b \tREG[%d]: %b", OUT1ADDRESS, OUT1, OUT2ADDRESS, OUT2);
        //$display("REG[0]: %b\nREG[1]: %b\nREG[2]: %b\nREG[3]: %b\nREG[4]: %b\nREG[5]: %b\nREG[6]: %b\nREG[7]: %b", REGISTER[0], REGISTER[1], REGISTER[2], REGISTER[3], REGISTER[4], REGISTER[5], REGISTER[6], REGISTER[7]);
      end

    // Synchronous Data Operations (WRITE, RESET)
    always @ (posedge CLK)
    begin
      // RESET (Highest Priority Operation)
      if (RESET == 1'b1) begin
        $display("RESET MEMORY");
        #1 for(i=0; i<8; i = i+1) begin
          REGISTER[i] = 8'b0000_0000;
        end
      end

      // WRITE
      else if (WRITE == 1'b1) begin
        //$display("REG[0]: %b\nREG[1]: %b\nREG[2]: %b\nREG[3]: %b\nREG[4]: %b\nREG[5]: %b\nREG[6]: %b\nREG[7]: %b", REGISTER[0], REGISTER[1], REGISTER[2], REGISTER[3], REGISTER[4], REGISTER[5], REGISTER[6], REGISTER[7]);
        $display("WRITE DATA\t REG: %d \tDATA: 0x%h", INADDRESS, IN);
        #1 REGISTER[INADDRESS] = IN; // Writing data to the given register
      end
    end

    always @ (INADDRESS, OUT1ADDRESS, OUT2ADDRESS, RESET) begin
      $display("REG[0]: 0x%h\nREG[1]: 0x%h\nREG[2]: 0x%h\nREG[3]: 0x%h\nREG[4]: 0x%h\nREG[5]: 0x%h\nREG[6]: 0x%h\nREG[7]: 0x%h", REGISTER[0], REGISTER[1], REGISTER[2], REGISTER[3], REGISTER[4], REGISTER[5], REGISTER[6], REGISTER[7]);
    end

endmodule

Group09_Lab05_Part3/or.v
/*
    * CO224 - Computer Architecture
    * Lab 05 - Part 3
    * or unit
    * Group 09 (E/20/148, E/20/157)
    * 2024-04-24
    * Version 1.0
*/


// ALU OR unit is used to do OR operation in the ALU
module myOR(DATA1, DATA2, RESULT);
    // Input-output Declaration
    input [7:0] DATA1, DATA2;
    output [7:0] RESULT;

    // Result
    assign #1 RESULT = DATA1 | DATA2;
endmodule

Group09_Lab05_Part3/and.v
/*
    * CO224 - Computer Architecture
    * Lab 05 - Part 3
    * and unit
    * Group 09 (E/20/148, E/20/157)
    * 2024-04-24
    * Version 1.0
*/


// ALU and unit is used to do and operation in the ALU
module myAND(DATA1, DATA2, RESULT);
    // Input-output Declaration
    input [7:0] DATA1, DATA2;
    output [7:0] RESULT;

    // Result
    assign #1 RESULT = DATA1 & DATA2;
endmodule

Group09_Lab05_Part3/add.v
/*
    * CO224 - Computer Architecture
    * Lab 05 - Part 3
    * add unit
    * Group 09 (E/20/148, E/20/157)
    * 2024-04-24
    * Version 1.0
*/


// ALU add unit is used to do add operation in the ALU
module add(DATA1, DATA2, RESULT);
    // Input-output Declaration
    input [7:0] DATA1, DATA2;
    output reg [7:0] RESULT;

    // Result
    always @ (DATA1, DATA2) begin
        #2 
        RESULT = DATA1 + DATA2;
        //$display("ADD Unit:: \tDATA1: %d \tDATA2: %d \tRESULT: %d", DATA1, DATA2, RESULT);
    end
endmodule

Group09_Lab05_Part4/forward.v
/*
    * CO224 - Computer Architecture
    * Lab 05 - Part 3
    * forward unit
    * Group 09 (E/20/148, E/20/157)
    * 2024-04-24
    * Version 1.0
*/


// FORWARD unit should simply send an operand value from DATA2 to its output. 
module forward(DATA2, RESULT);
    // Input-output Declaration
    input [7:0] DATA2;
    output [7:0] RESULT;

    // Result
    assign #1 RESULT = DATA2;
endmodule

Group09_Lab05_Part3/alu.v
/*
    * CO224 - Computer Architecture
    * Lab 05 - Part 3
    * ALU unit
    * Group 09 (E/20/148, E/20/157)
    * 2024-04-24
    * Version 1.0
*/

`include "forward.v"
`include "add.v"
`include "and.v"
`include "or.v"

// ALU unit is used to provide suitable output according to the selector value. 
module alu(DATA1, DATA2, RESULT, SELECT);
    // Input-output Declaration
    input [7:0] DATA1, DATA2;
    input [2:0] SELECT;
    output reg [7:0] RESULT;

    wire [7:0] addOut, andOut, fwdOut, orOut, compOut, subOut;

    // Making functional Units
    forward fwdUnit(DATA2, fwdOut);
    add addUnit(DATA1, DATA2, addOut);
    myAND andUnit(DATA1, DATA2, andOut);
    myOR orUnit(DATA1, DATA2, orOut);
    
    // Multiplexing according to selector values
    always @ (SELECT, fwdOut, addOut, andOut, orOut)
    begin
      case (SELECT)		//Case statement to switch between the outputs

			3'b000 :	RESULT = fwdOut;    //SELECT = 0 : FORWARD
			
			3'b001 :	RESULT = addOut;		//SELECT = 1 : ADD
			
			3'b010 :	RESULT = andOut;		//SELECT = 2 : AND
			
			3'b011 :	RESULT = orOut;		  //SELECT = 3 : OR

		endcase 

    //$display("DATA1: %b  \tDATA2: %b  \tSELECT: %b  \tRESULT: %b", DATA1, DATA2, SELECT, RESULT);

    end

    endmodule

Group09_Lab05_Part3/cpu.v
/*
    * CO224 - Computer Architecture
    * Lab 05 - Part 3
    * CPU module
    * Group 09 (E/20/148, E/20/157)
    * 2024-04-24
    * Version 1.0
*/

// Importing external modules
`include "alu.v"
`include "reg_file.v"
`include "mux.v"
`include "complement.v"

module cpu(PC, INSTRUCTION, CLK, RESET);
    /* -------------------------------- Input-output Declaration -------------------------------- */

    input[31:0] INSTRUCTION;   // 32-bit bus
    input CLK, RESET;          // Single ports

    output reg[31:0] PC;       // 32-bit bus

    /* ------------------------------------------------------------------------------------------ */



    /* -------------------------------- Local Nets and Registers -------------------------------- */

    // Tempary stored location for next PC instruction
    reg[31:0] tempPC;

    // Connections for ALU
    wire[7:0] ALURESULT;
    reg[2:0] ALUOP;

    // Connections for 8x8 register file
    wire[7:0] REGOUT1, REGOUT2;
    reg[2:0] READREG1, READREG2, WRITEREG;
    reg WRITEENABLE;

    // Data Bus for OPCODES
    reg[7:0] OPCODE;

    // Data Bus for IMMEDIATE Value
    reg[7:0] IMMEDIATE;

    // 2's Complement Output
    wire[7:0] twos_Complemet;

    // Inputs and outputs for SubMux
    wire[7:0] subMuxOut;
    reg subMuxSelect;

    // Inputs and outputs for ImmediateMux
    wire[7:0] immMuxOut;
    reg immMuxSelect;

    /* ------------------------------------------------------------------------------------------ */



    /* -------------------------------- Making Functional Units --------------------------------- */

    alu aluUnit(REGOUT1, immMuxOut, ALURESULT, ALUOP);
    reg_file regUnit(ALURESULT, REGOUT1, REGOUT2, WRITEREG, READREG1, READREG2, WRITEENABLE, CLK, RESET);
    mux subMux(REGOUT2, twos_Complemet, subMuxSelect, subMuxOut);
    mux immediateMux(IMMEDIATE, subMuxOut, immMuxSelect, immMuxOut);
    complement complementUnit(REGOUT2, twos_Complemet);

    /* ------------------------------------------------------------------------------------------ */




    /* -------------------------------- Program Counter Functions ------------------------------- */
    // Calculating Next Instruction
    always@(PC)
    begin
      #1 tempPC = PC + 4;
    end

    // Goto Next Instruction
    always@ (posedge CLK)
    begin
      if(RESET == 1) begin  // RESET PC to zero and Pass to the Instruction Register 
        $display("RESET PC");
        #1
        PC = 0;
        tempPC = 0;
      end
      else begin            // Pass Calculated PC Value to the Instruction Register
        #1 PC = tempPC;
      end

      $display("\nPC: %b", PC);
    end

    /* ------------------------------------------------------------------------------------------ */



    /* --------------------------------- Control Unit Functions --------------------------------- */

    /*
        NOTE: All instructions are of 32-bit fixed length, and encoded in the format shown below.

        +----------------------+----------------------+---------------------+--------------------+
        |        OP-CODE       |       RD / IMM       |          RT         |      RS / IMM      |
        |     (bits 31-24)     |     (bits 23-16)     |     (bits 15-8)     |     (bits 7-0)     |
        +----------------------+----------------------+---------------------+--------------------+

        * Bits(31-24): OP-CODE field identifies the instruction's operation. This should be used 
                       by the control logic to interpret the remaining fields and derive the 
                       control signals. 

        * Bits(23-16): A register (RD) to be written to in the register file, or an immediate value 
                       (jump or branch target offset). 

        * Bits(15-8):  A register (RT) to be read from in the register file. 

        * Bits(7-0):   A register (RS) to be read from in the register file, or an immediate value. 
    */    

    // Instruction Decording
    always @ (INSTRUCTION)
    begin
      $display("INSTRCTION: %b", INSTRUCTION);
          
      // Fetching out Sub Instructions
      OPCODE    <= INSTRUCTION[31:24]; // OPCODE
      WRITEREG  <= INSTRUCTION[23:16]; // Address of the write register
      READREG1  <= INSTRUCTION[15:8];  // Address of the read register 1
      READREG2  <= INSTRUCTION[7:0];   // Address of the read register 2
      IMMEDIATE <= INSTRUCTION[7:0];   // Immediate value
      $display("OPCODE: %b\t RD: %d\t RT: %d\tRS: %d \tIMM: 0x%h", OPCODE, WRITEREG, READREG1, READREG2, IMMEDIATE);

      #1  // Latency for Instruction Decoding

      case (OPCODE)

        // Load Instruction
        8'b0000_0000: begin
                        $display("Loadi");
                        immMuxSelect <= 0; // Select immediate value                        
                        ALUOP <= 0;        // ALU FORWARD 
                        WRITEENABLE <= 1;  // Writing pulse on
                      end

        // Move
        8'b0000_0001: begin
                        $display("Move");
                        subMuxSelect <= 0; // Select the original register 2 value
                        immMuxSelect <= 1; // Select register value
                        ALUOP = 0;        // ALU FORWARD 
                        WRITEENABLE <= 1;  // Writing pulse on
                      end

        // Add
        8'b0000_0010: begin
                        $display("Add");
                        subMuxSelect <= 0; // Select the original register 2 value
                        immMuxSelect <= 1; // Select register value
                        ALUOP <= 1;        // ALU ADD 
                        WRITEENABLE <= 1;  // Writing pulse on
                      end

        // Sub
        8'b0000_0011: begin
                        $display("Sub");
                        subMuxSelect <= 1; // Select the 2's complement value
                        immMuxSelect <= 1; // Select register value
                        ALUOP <= 1;        // ALU ADD 
                        WRITEENABLE <= 1;  // Writing pulse on
                      end


        // AND
        8'b0000_0100: begin
                        $display("AND");
                        subMuxSelect <= 0; // Select the original register 2 value
                        immMuxSelect <= 1; // Select register value
                        ALUOP <= 2;        // ALU AND 
                        WRITEENABLE <= 1;  // Writing pulse on
                      end

        // OR
        8'b0000_0101: begin
                        $display("OR");
                        subMuxSelect <= 1; // Select the original register 2 value
                        immMuxSelect <= 1; // Select register value
                        ALUOP <= 3;        // ALU OR 
                        WRITEENABLE <= 1;  // Writing pulse on
                      end
      endcase      

      #6 WRITEENABLE = 0; // Desable Writing

    end

    /* ------------------------------------------------------------------------------------------ */

endmodule

Group09_Lab05_Part3/cpu_tb.v
// Computer Architecture (CO224) - Lab 05
// Design: Testbench of Integrated CPU of Simple Processor
// Author: Isuru Nawinne
// Modified by: Janakantha S.M.B.G.
// Last Modified: 24/04/2024

`include "cpu.v"


module cpu_tb;

    reg CLK, RESET;
    wire [31:0] PC;
    reg [31:0] INSTRUCTION;
    
    /* 
    ------------------------
     SIMPLE INSTRUCTION MEM
    ------------------------
    */
    
    // TODO: Initialize an array of registers (8x1024) named 'instr_mem' to be used as instruction memory
    reg[7:0] instr_mem[1023:0];
    
    // TODO: Create combinational logic to support CPU instruction fetching, given the Program Counter(PC) value 
    //       (make sure you include the delay for instruction fetching here)
    always @ (PC)
    begin
        #2 
        INSTRUCTION[31:24] = instr_mem[PC+3];
        INSTRUCTION[23:16] = instr_mem[PC+2];
        INSTRUCTION[15:8]  = instr_mem[PC+1];
        INSTRUCTION[7:0]   = instr_mem[PC];
    end
    
    initial
    begin
        // Initialize instruction memory with the set of instructions you need execute on CPU
        
        // METHOD 1: manually loading instructions to instr_mem 
        {instr_mem[3], instr_mem[2], instr_mem[1], instr_mem[0]}     = 32'b00000000_00000000_00000000_00001001; // Loadi 0 0x09
        {instr_mem[7], instr_mem[6], instr_mem[5], instr_mem[4]}     = 32'b00000000_00000001_00000000_00000001; // loadi 1 0x01
        {instr_mem[11], instr_mem[10], instr_mem[9], instr_mem[8]}   = 32'b00000010_00000110_00000001_00000000; // add 6 1 0
        {instr_mem[15], instr_mem[14], instr_mem[13], instr_mem[12]} = 32'b00000001_00000000_00000000_00000110; // mov 0 6
        {instr_mem[19], instr_mem[18], instr_mem[17], instr_mem[16]} = 32'b00000000_00000001_00000000_00000001; // loadi 1 0x01
        {instr_mem[23], instr_mem[22], instr_mem[21], instr_mem[20]} = 32'b00000010_00000010_00000010_00000001; // add 2 2 1
        
        // METHOD 2: loading instr_mem content from instr_mem.mem file
        //$readmemb("instr_mem.mem", instr_mem);
    end
    
    /* 
    -----
     CPU
    -----
    */
    cpu mycpu(PC, INSTRUCTION, CLK, RESET);

    integer i;

    initial begin
        // generate files needed to plot the waveform using GTKWave
        $dumpfile("cpu_wavedata.vcd");
		$dumpvars(0, mycpu);
        
        for (i=0; i<8; i=i+1)
            $dumpvars(1, mycpu.regUnit.REGISTER[i]);
        
        RESET = 1'b0;
        CLK = 1'b0;
        
        // TODO: Reset the CPU (by giving a pulse to RESET signal) to start the program execution
        RESET = 1;
        #6
        RESET = 0;
        // finish simulation after some time
        #100
        $finish;
    end
    
    // clock signal generation
    always
        #4 CLK = ~CLK;
        

endmodule

Group09_Lab05_Part3/cpu_wavedata.vcd
$date
	Thu Jun 13 11:53:54 2024
$end
$version
	Icarus Verilog
$end
$timescale
	1s
$end
$scope module cpu_tb $end
$scope module mycpu $end
$var wire 1 ! CLK $end
$var wire 32 " INSTRUCTION [31:0] $end
$var wire 1 # RESET $end
$var wire 8 $ twos_Complemet [7:0] $end
$var wire 8 % subMuxOut [7:0] $end
$var wire 8 & immMuxOut [7:0] $end
$var wire 8 ' REGOUT2 [7:0] $end
$var wire 8 ( REGOUT1 [7:0] $end
$var wire 8 ) ALURESULT [7:0] $end
$var reg 3 * ALUOP [2:0] $end
$var reg 8 + IMMEDIATE [7:0] $end
$var reg 8 , OPCODE [7:0] $end
$var reg 32 - PC [31:0] $end
$var reg 3 . READREG1 [2:0] $end
$var reg 3 / READREG2 [2:0] $end
$var reg 1 0 WRITEENABLE $end
$var reg 3 1 WRITEREG [2:0] $end
$var reg 1 2 immMuxSelect $end
$var reg 1 3 subMuxSelect $end
$var reg 32 4 tempPC [31:0] $end
$scope module aluUnit $end
$var wire 3 5 SELECT [2:0] $end
$var wire 8 6 orOut [7:0] $end
$var wire 8 7 fwdOut [7:0] $end
$var wire 8 8 andOut [7:0] $end
$var wire 8 9 addOut [7:0] $end
$var wire 8 : DATA2 [7:0] $end
$var wire 8 ; DATA1 [7:0] $end
$var reg 8 < RESULT [7:0] $end
$scope module addUnit $end
$var wire 8 = DATA2 [7:0] $end
$var wire 8 > DATA1 [7:0] $end
$var reg 8 ? RESULT [7:0] $end
$upscope $end
$scope module andUnit $end
$var wire 8 @ RESULT [7:0] $end
$var wire 8 A DATA2 [7:0] $end
$var wire 8 B DATA1 [7:0] $end
$upscope $end
$scope module fwdUnit $end
$var wire 8 C RESULT [7:0] $end
$var wire 8 D DATA2 [7:0] $end
$upscope $end
$scope module orUnit $end
$var wire 8 E RESULT [7:0] $end
$var wire 8 F DATA2 [7:0] $end
$var wire 8 G DATA1 [7:0] $end
$upscope $end
$upscope $end
$scope module complementUnit $end
$var wire 8 H RESULT [7:0] $end
$var wire 8 I DATA2 [7:0] $end
$upscope $end
$scope module immediateMux $end
$var wire 8 J IN1 [7:0] $end
$var wire 1 2 SELECT $end
$var wire 8 K IN2 [7:0] $end
$var reg 8 L OUT [7:0] $end
$upscope $end
$scope module regUnit $end
$var wire 1 ! CLK $end
$var wire 8 M IN [7:0] $end
$var wire 3 N INADDRESS [2:0] $end
$var wire 3 O OUT1ADDRESS [2:0] $end
$var wire 3 P OUT2ADDRESS [2:0] $end
$var wire 1 # RESET $end
$var wire 1 0 WRITE $end
$var reg 8 Q OUT1 [7:0] $end
$var reg 8 R OUT2 [7:0] $end
$var integer 32 S i [31:0] $end
$upscope $end
$scope module subMux $end
$var wire 8 T IN1 [7:0] $end
$var wire 8 U IN2 [7:0] $end
$var wire 1 3 SELECT $end
$var reg 8 V OUT [7:0] $end
$upscope $end
$upscope $end
$upscope $end
$scope module cpu_tb $end
$scope module mycpu $end
$scope module regUnit $end
$var reg 8 W \REGISTER[0] [7:0] $end
$upscope $end
$upscope $end
$upscope $end
$scope module cpu_tb $end
$scope module mycpu $end
$scope module regUnit $end
$var reg 8 X \REGISTER[1] [7:0] $end
$upscope $end
$upscope $end
$upscope $end
$scope module cpu_tb $end
$scope module mycpu $end
$scope module regUnit $end
$var reg 8 Y \REGISTER[2] [7:0] $end
$upscope $end
$upscope $end
$upscope $end
$scope module cpu_tb $end
$scope module mycpu $end
$scope module regUnit $end
$var reg 8 Z \REGISTER[3] [7:0] $end
$upscope $end
$upscope $end
$upscope $end
$scope module cpu_tb $end
$scope module mycpu $end
$scope module regUnit $end
$var reg 8 [ \REGISTER[4] [7:0] $end
$upscope $end
$upscope $end
$upscope $end
$scope module cpu_tb $end
$scope module mycpu $end
$scope module regUnit $end
$var reg 8 \ \REGISTER[5] [7:0] $end
$upscope $end
$upscope $end
$upscope $end
$scope module cpu_tb $end
$scope module mycpu $end
$scope module regUnit $end
$var reg 8 ] \REGISTER[6] [7:0] $end
$upscope $end
$upscope $end
$upscope $end
$scope module cpu_tb $end
$scope module mycpu $end
$scope module regUnit $end
$var reg 8 ^ \REGISTER[7] [7:0] $end
$upscope $end
$upscope $end
$upscope $end
$enddefinitions $end
$comment Show the parameter values. $end
$dumpall
$end
#0
$dumpvars
bx ^
bx ]
bx \
bx [
bx Z
bx Y
bx X
bx W
bx V
bx U
bx T
bx S
bx R
bx Q
bx P
bx O
bx N
bx M
bx L
bx K
bx J
bx I
bx H
bx G
bx F
bx E
bx D
bx C
bx B
bx A
bx @
bx ?
bx >
bx =
bx <
bx ;
bx :
bx 9
bx 8
bx 7
bx 6
bx 5
bx 4
x3
x2
bx 1
x0
bx /
bx .
bx -
bx ,
bx +
bx *
bx )
bx (
bx '
bx &
bx %
bx $
1#
bx "
0!
$end
#4
1!
#5
b0 ^
b0 ]
b0 \
b0 [
b0 Z
b0 Y
b0 X
b0 W
b1000 S
b0 4
b0 -
#6
b100 4
0#
#7
b1001 +
b1001 J
b1 /
b1 P
b0 .
b0 O
b0 1
b0 N
b0 ,
b1001 "
#8
b1001 &
b1001 :
b1001 =
b1001 A
b1001 D
b1001 F
b1001 L
10
b0 *
b0 5
02
0!
#9
b1001 )
b1001 <
b1001 M
bx1xx1 6
bx1xx1 E
b0x00x 8
b0x00x @
b1001 7
b1001 C
b0 '
b0 I
b0 R
b0 T
b0 (
b0 ;
b0 >
b0 B
b0 G
b0 Q
#10
b0 $
b0 H
b0 U
b1001 6
b1001 E
b0 8
b0 @
b1001 9
b1001 ?
#12
1!
#13
b100 -
b1001 W
#14
b1000 4
00
#15
b1 &
b1 :
b1 =
b1 A
b1 D
b1 F
b1 L
b1 +
b1 J
b1 1
b1 N
b10000000000000001 "
#16
10
b1 )
b1 <
b1 M
b1 6
b1 E
b1 7
b1 C
0!
#17
b1 9
b1 ?
#20
1!
#21
b1 X
b1000 -
#22
b1100 4
00
#23
b0 &
b0 :
b0 =
b0 A
b0 D
b0 F
b0 L
b0 +
b0 J
b0 /
b0 P
b1 .
b1 O
b110 1
b110 N
b10 ,
b10000001100000000100000000 "
#24
b0 %
b0 K
b0 V
10
b1 *
b1 5
12
03
b1 )
b1 <
b1 M
b0 6
b0 E
b0 7
b0 C
0!
#25
b1001 &
b1001 :
b1001 =
b1001 A
b1001 D
b1001 F
b1001 L
b1001 %
b1001 K
b1001 V
b1001 '
b1001 I
b1001 R
b1001 T
b1 (
b1 ;
b1 >
b1 B
b1 G
b1 Q
#26
b1 8
b1 @
b1001 7
b1001 C
b11110111 $
b11110111 H
b11110111 U
b1001 6
b1001 E
#27
b1010 )
b1010 <
b1010 M
b1010 9
b1010 ?
#28
1!
#29
b1100 -
b1010 ]
#30
b10000 4
00
#31
b110 +
b110 J
b110 /
b110 P
b0 .
b0 O
b0 1
b0 N
b1 ,
b1000000000000000000000110 "
#32
10
b1001 )
b1001 <
b1001 M
b0 *
b0 5
0!
#33
b1010 &
b1010 :
b1010 =
b1010 A
b1010 D
b1010 F
b1010 L
b1010 %
b1010 K
b1010 V
b1010 '
b1010 I
b1010 R
b1010 T
b1001 (
b1001 ;
b1001 >
b1001 B
b1001 G
b1001 Q
#34
b1010 )
b1010 <
b1010 M
b1011 6
b1011 E
b1010 7
b1010 C
b11110110 $
b11110110 H
b11110110 U
b1000 8
b1000 @
#35
b10011 9
b10011 ?
#36
1!
#37
b1010 W
b10000 -
#38
b10100 4
00
#39
b1 +
b1 J
b1 /
b1 P
b1 1
b1 N
b0 ,
b10000000000000001 "
#40
b1 &
b1 :
b1 =
b1 A
b1 D
b1 F
b1 L
10
02
0!
#41
b1 )
b1 <
b1 M
b1 %
b1 K
b1 V
b1001 6
b1001 E
b1 8
b1 @
b1 7
b1 C
b1 '
b1 I
b1 R
b1 T
b1010 (
b1010 ;
b1010 >
b1010 B
b1010 G
b1010 Q
#42
b11111111 $
b11111111 H
b11111111 U
b1011 6
b1011 E
b0 8
b0 @
b1011 9
b1011 ?
#44
1!
#45
b10100 -
b1 X
#46
b11000 4
00
#47
b10 .
b10 O
b10 1
b10 N
b10 ,
b10000000100000001000000001 "
#48
b1011 )
b1011 <
b1011 M
10
b1 *
b1 5
12
0!
#49
b0 (
b0 ;
b0 >
b0 B
b0 G
b0 Q
#50
b1 6
b1 E
#51
b1 )
b1 <
b1 M
b1 9
b1 ?
#52
1!
#53
b1 Y
b11000 -
#54
b11100 4
00
#55
bx +
bx J
bx /
bx P
bx .
bx O
bx 1
bx N
bx ,
bx "
#56
0!
#57
bx &
bx :
bx =
bx A
bx D
bx F
bx L
bx %
bx K
bx V
bx '
bx I
bx R
bx T
bx (
bx ;
bx >
bx B
bx G
bx Q
#58
bx 7
bx C
bx $
bx H
bx U
bx 6
bx E
bx 8
bx @
#59
bx )
bx <
bx M
bx 9
bx ?
#60
1!
#61
b11100 -
#62
b100000 4
#64
0!
#68
1!
#69
b100000 -
#70
b100100 4
#72
0!
#76
1!
#77
b100100 -
#78
b101000 4
#80
0!
#84
1!
#85
b101000 -
#86
b101100 4
#88
0!
#92
1!
#93
b101100 -
#94
b110000 4
#96
0!
#100
1!
#101
b110000 -
#102
b110100 4
