Group09_Lab05_Part4/complement.v
/*
    * CO224 - Computer Architecture
    * Lab 05 - Part 3
    * 2's Complement Unit
    * Group 09 (E/20/148, E/20/157)
    * 2024-04-24
    * Version 1.0
*/


// This module is used to produce 2's complement value of a given 8 bit data set
module complement(DATA2, RESULT);
    // Input-output Declaration
    input [7:0] DATA2;
    output [7:0] RESULT;

    // Result
    assign #1 RESULT = ~DATA2 + 8'b0000_0001;

    /*initial begin
        $monitor("DATA=%b,  RESULT=%b\n", DATA2, RESULT);
    end*/

endmodule

Group09_Lab05_Part4/mux.v
/*
    * CO224 - Computer Architecture
    * Lab 05 - Part 3
    * Multiplexer unit
    * Group 09 (E/20/148, E/20/157)
    * 2024-04-24
    * Version 1.0
*/

module mux(IN1, IN2, SELECT, OUT);
    // Input-output Declaration
    input[7:0] IN1, IN2;
    input SELECT;

    output reg[7:0] OUT;

    // Operation
    always @ (IN1, IN2, SELECT)
    begin
      if(SELECT == 0) begin
        OUT = IN1;
      end

      else if(SELECT == 1) begin
        OUT = IN2;
      end

     //$display("IN1: %b \t IN2: %b \t S: %b \t OUT: %b", IN1, IN2, SELECT, OUT);
    end

endmodule

Group09_Lab05_Part4/reg_file.v
/*
    * CO224 - Computer Architecture
    * Lab 05 - Part 3
    * reg_file module
    * Group 09 (E/20/148, E/20/157)
    * 2024-04-24
    * Version 1.0
*/

module reg_file(IN, OUT1, OUT2, INADDRESS, OUT1ADDRESS, OUT2ADDRESS, WRITE, CLK, RESET);
    // Port declaration
    input [7:0] IN; // Data input for writing
    input [7:0] INADDRESS; 
    input [7:0] OUT1ADDRESS, OUT2ADDRESS; // Data addresses


    input CLK, RESET, WRITE; // Control signals

    output reg [7:0] OUT1, OUT2; // Data outputs

    // Register Allocation
    reg [7:0] REGISTER [7:0]; // 8 x 8 register block

    // variable for counting
    integer i;

    // Asynchronous Data Operations (READ)
    always @ (OUT1ADDRESS, OUT2ADDRESS)
    begin
      //if (WRITE == 1'b0) begin
        #2   // Artificial delay of 2 time units
        OUT1 = REGISTER[OUT1ADDRESS[2:0]];
        OUT2 = REGISTER[OUT2ADDRESS[2:0]];
        //$display("READ DATA:: \tREG[%d]: %b \tREG[%d]: %b", OUT1ADDRESS, OUT1, OUT2ADDRESS, OUT2);
        //$display("REG[0]: %b\nREG[1]: %b\nREG[2]: %b\nREG[3]: %b\nREG[4]: %b\nREG[5]: %b\nREG[6]: %b\nREG[7]: %b", REGISTER[0], REGISTER[1], REGISTER[2], REGISTER[3], REGISTER[4], REGISTER[5], REGISTER[6], REGISTER[7]);
      end

    // Synchronous Data Operations (WRITE, RESET)
    always @ (posedge CLK)
    begin
      // RESET (Highest Priority Operation)
      if (RESET == 1'b1) begin
        $display("RESET MEMORY");
        #1 for(i=0; i<8; i = i+1) begin
          REGISTER[i] = 8'b0000_0000;
        end
      end

      // WRITE
      else if (WRITE == 1'b1) begin
        //$display("REG[0]: %b\nREG[1]: %b\nREG[2]: %b\nREG[3]: %b\nREG[4]: %b\nREG[5]: %b\nREG[6]: %b\nREG[7]: %b", REGISTER[0], REGISTER[1], REGISTER[2], REGISTER[3], REGISTER[4], REGISTER[5], REGISTER[6], REGISTER[7]);
        $display("WRITE DATA\t REG: %d \tDATA: 0x%h", INADDRESS, IN);
        #1 REGISTER[INADDRESS[2:0]] = IN; // Writing data to the given register
      end
    end

    always @ (INADDRESS, OUT1ADDRESS, OUT2ADDRESS, RESET) begin
      $display("REG[0]: 0x%h\nREG[1]: 0x%h\nREG[2]: 0x%h\nREG[3]: 0x%h\nREG[4]: 0x%h\nREG[5]: 0x%h\nREG[6]: 0x%h\nREG[7]: 0x%h", REGISTER[0], REGISTER[1], REGISTER[2], REGISTER[3], REGISTER[4], REGISTER[5], REGISTER[6], REGISTER[7]);
    end

endmodule

Group09_Lab05_Part4/add.v
/*
    * CO224 - Computer Architecture
    * Lab 05 - Part 4
    * add unit
    * Group 09 (E/20/148, E/20/157)
    * 2024-05-06
    * Version 2.0
*/


// ALU add unit is used to do add operation in the ALU
module add(DATA1, DATA2, RESULT);
    // Input-output Declaration
    input [7:0] DATA1, DATA2;
    output [7:0] RESULT;
    //output reg [7:0] RESULT;

    // Result
    assign #2 RESULT = DATA1 + DATA2;
    
    /*
    always @ (DATA1, DATA2) begin
        #2 
        RESULT = DATA1 + DATA2;
        //$display("ADD Unit:: \tDATA1: %d \tDATA2: %d \tRESULT: %d", DATA1, DATA2, RESULT);
    end
    */

endmodule

Group09_Lab05_Part1/or.v
/*
    * CO224 - Computer Architecture
    * Lab 05 - Part 1
    * or unit
    * Group 09 (E/20/148, E/20/157)
    * 2024-04-09
    * Version 1.0
*/


// ALU OR unit is used to do OR operation in the ALU
module myOR(DATA1, DATA2, RESULT);
    // Input-output Declaration
    input [7:0] DATA1, DATA2;
    output [7:0] RESULT;

    // Result
    assign #1 RESULT = DATA1 | DATA2;
endmodule

Group09_Lab05_Part3/and.v
/*
    * CO224 - Computer Architecture
    * Lab 05 - Part 3
    * and unit
    * Group 09 (E/20/148, E/20/157)
    * 2024-04-24
    * Version 1.0
*/


// ALU and unit is used to do and operation in the ALU
module myAND(DATA1, DATA2, RESULT);
    // Input-output Declaration
    input [7:0] DATA1, DATA2;
    output [7:0] RESULT;

    // Result
    assign #1 RESULT = DATA1 & DATA2;
endmodule

Group09_Lab05_Part4/forward.v
/*
    * CO224 - Computer Architecture
    * Lab 05 - Part 3
    * forward unit
    * Group 09 (E/20/148, E/20/157)
    * 2024-04-24
    * Version 1.0
*/


// FORWARD unit should simply send an operand value from DATA2 to its output. 
module forward(DATA2, RESULT);
    // Input-output Declaration
    input [7:0] DATA2;
    output [7:0] RESULT;

    // Result
    assign #1 RESULT = DATA2;
endmodule

Group09_Lab05_Part4/alu.v
/*
    * CO224 - Computer Architecture
    * Lab 05 - Part 4
    * ALU unit
    * Group 09 (E/20/148, E/20/157)
    * 2024-05-07
    * Version 2.0
*/

`include "forward.v"
`include "add.v"
`include "and.v"
`include "or.v"

// Note: ZERO signal is implemented

// ALU unit is used to provide suitable output according to the selector value. 
module alu(DATA1, DATA2, RESULT, ZERO, SELECT);
    // Input-output Declaration
    input [7:0] DATA1, DATA2;
    input [2:0] SELECT;
    output reg [7:0] RESULT;
    output reg ZERO;

    wire [7:0] addOut, andOut, fwdOut, orOut, compOut, subOut;

    // Making functional Units
    forward fwdUnit(DATA2, fwdOut);
    add addUnit(DATA1, DATA2, addOut);
    myAND andUnit(DATA1, DATA2, andOut);
    myOR orUnit(DATA1, DATA2, orOut);
    
    // Multiplexing according to selector values
    always @ (SELECT, fwdOut, addOut, andOut, orOut)
    begin
      ZERO = 0; // Always set ZERO to 0 (To disable the signal)

      case (SELECT)		//Case statement to switch between the outputs

			3'b000 :	RESULT = fwdOut;    //SELECT = 0 : FORWARD
			
			3'b001 :	begin     
                  RESULT = addOut;  //SELECT = 1 : ADD
                  if (RESULT == 0) begin
                    ZERO = 1'b1;    //Enable the ZERO signal
                  end
                end
			
			3'b010 :	RESULT = andOut;		//SELECT = 2 : AND
			
			3'b011 :	RESULT = orOut;		  //SELECT = 3 : OR

		endcase 

    //$display("DATA1: %b  \tDATA2: %b  \tSELECT: %b  \tRESULT: %b", DATA1, DATA2, SELECT, RESULT);

    end

    endmodule

Group09_Lab05_Part4/cpu.v
/*
    * CO224 - Computer Architecture
    * Lab 05 - Part 3
    * CPU module
    * Group 09 (E/20/148, E/20/157)
    * 2024-05-06
    * Version 5.1
*/

// Note: The JUMP Instruction is implemented
// Note: The BEQ Instruction is implemented

// Importing external modules
`include "alu.v"
`include "reg_file.v"
`include "mux.v"
`include "complement.v"

module cpu(PC, INSTRUCTION, CLK, RESET);
    /* -------------------------------- Input-output Declaration -------------------------------- */

    input[31:0] INSTRUCTION;   // 32-bit bus
    input CLK, RESET;          // Single ports

    output reg[31:0] PC;       // 32-bit bus

    /* ------------------------------------------------------------------------------------------ */



    /* -------------------------------- Local Nets and Registers -------------------------------- */

    // Tempary stored location for next PC instruction
    reg[7:0] nextPC;  
    /* 
      Note: Our Instruction memory is 8x1024 size. Then it has 1024 spaces for 8 bit words. The size of one instruction is 32 bit. 
      That means one instruction is a size of 4 words in instruction memory. So, the maximum instructions that can be store in the 
      instruction memory is 256. In binary we need maximum 8 bits to address the all of the memory locations in the instruction memory.
      Then, minimum 8 bits are sufficient in PC to access the Instruction memory.
    */

    // Connections for ALU
    wire[7:0] ALURESULT;
    reg[2:0] ALUOP;
    wire ZERO;

    // Connections for PC Adder Unit
    wire[7:0] pcAdderOut;

    // Connections for Branch Mux Unit
    reg BRANCH;
    //wire branchEnable;
    wire[7:0] branchMuxOut;

    // Connections for Jump Mux Unit
    reg JUMP;
    wire[7:0] jumpMuxOut;

    // Connections for 8x8 register file
    wire[7:0] REGOUT1, REGOUT2;
    reg[7:0] READREG1, READREG2, WRITEREG;
    reg WRITEENABLE;

    // Data Bus for OPCODES
    reg[7:0] OPCODE;

    // Data Bus for IMMEDIATE Value
    reg[7:0] IMMEDIATE1, IMMEDIATE2;

    // 2's Complement Output
    wire[7:0] twos_Complemet;

    // Inputs and outputs for SubMux
    wire[7:0] subMuxOut;
    reg subMuxSelect;

    // Inputs and outputs for ImmediateMux
    wire[7:0] immMuxOut;
    reg immMuxSelect;

    /* ------------------------------------------------------------------------------------------ */



    /* -------------------------------- Making Functional Units --------------------------------- */

    alu aluUnit(REGOUT1, immMuxOut, ALURESULT, ZERO, ALUOP);
    add pcAdder(nextPC, IMMEDIATE1<<2, pcAdderOut);
    reg_file regUnit(ALURESULT, REGOUT1, REGOUT2, WRITEREG, READREG1, READREG2, WRITEENABLE, CLK, RESET);
    mux subMux(REGOUT2, twos_Complemet, subMuxSelect, subMuxOut);
    mux immediateMux(IMMEDIATE2, subMuxOut, immMuxSelect, immMuxOut);
    mux jumpMux(branchMuxOut, pcAdderOut, JUMP, jumpMuxOut);
    mux branchMux(nextPC, pcAdderOut, (BRANCH & ZERO), branchMuxOut);
    complement complementUnit(REGOUT2, twos_Complemet);

    /* ------------------------------------------------------------------------------------------ */




    /* -------------------------------- Program Counter Functions ------------------------------- */
    // Calculating Next Instruction
    always@(PC)
    begin
      #1 nextPC = PC + 4;
    end

    // Goto Next Instruction
    always@ (posedge CLK)
    begin
      if(RESET == 1) begin  // RESET PC to zero and Pass to the Instruction Register 
        $display("RESET PC");
        #1
        PC <= 0;
        nextPC <= 0;
        //jump <= 0;
      end
      else begin            // Pass Calculated PC Value to the Instruction Register
        #1 PC = jumpMuxOut;
      end

      $display("\nnextPC: %b \tPCAdder: %b", nextPC, pcAdderOut);
      $display("Branch: %b \tZERO: %b \tBranchOut: %b", BRANCH, ZERO, branchMuxOut);
      $display("Jump: %b \nPC: %b", JUMP, PC);
    end

    /* ------------------------------------------------------------------------------------------ */



    /* --------------------------------- Control Unit Functions --------------------------------- */

    /*
        NOTE: All instructions are of 32-bit fixed length, and encoded in the format shown below.

        +----------------------+----------------------+---------------------+--------------------+
        |        OP-CODE       |      RD / IMM_1      |          RT         |     RS / IMM_2     |
        |     (bits 31-24)     |     (bits 23-16)     |     (bits 15-8)     |     (bits 7-0)     |
        +----------------------+----------------------+---------------------+--------------------+

        * Bits(31-24): OP-CODE field identifies the instruction's operation. This should be used 
                       by the control logic to interpret the remaining fields and derive the 
                       control signals. 

        * Bits(23-16): A register (RD) to be written to in the register file, or an immediate value 
                       (jump or branch target offset). 

        * Bits(15-8):  A register (RT) to be read from in the register file. 

        * Bits(7-0):   A register (RS) to be read from in the register file, or an immediate value. 
    */    

    // Instruction Decording
    always @ (INSTRUCTION)
    begin
      // Reset Control Signals
      JUMP = 0;
      BRANCH = 0;
      //subMuxSelect <= 0;
      //immMuxSelect <= 0;

      $display("INSTRCTION: %b", INSTRUCTION);
          
      // Fetching out Sub Instructions
      OPCODE     <= INSTRUCTION[31:24]; // OPCODE
      WRITEREG   <= INSTRUCTION[23:16]; // Address of the write register
      READREG1   <= INSTRUCTION[15:8];  // Address of the read register 1
      READREG2   <= INSTRUCTION[7:0];   // Address of the read register 2
      IMMEDIATE1 <= INSTRUCTION[23:16]; // Immediate value 1
      IMMEDIATE2 <= INSTRUCTION[7:0];   // Immediate value 2
      $display("OPCODE: %b\t RD: %d\t RT: %d\tRS: %d \tIMM1: 0x%h \tIMM2: 0x%h", OPCODE, WRITEREG, READREG1, READREG2, IMMEDIATE1, IMMEDIATE2);

      #1  // Latency for Instruction Decoding

      case (OPCODE)

        // Load Instruction
        8'b0000_0000: begin
                        $display("Loadi");
                        immMuxSelect <= 0; // Select immediate value                        
                        ALUOP <= 0;        // ALU FORWARD 
                        WRITEENABLE <= 1;  // Writing pulse on
                      end

        // Move
        8'b0000_0001: begin
                        $display("Move");
                        subMuxSelect <= 0; // Select the original register 2 value
                        immMuxSelect <= 1; // Select register value
                        ALUOP <= 0;        // ALU FORWARD 
                        WRITEENABLE <= 1;  // Writing pulse on
                      end

        // Add
        8'b0000_0010: begin
                        $display("Add");
                        subMuxSelect <= 0; // Select the original register 2 value
                        immMuxSelect <= 1; // Select register value
                        ALUOP <= 1;        // ALU ADD 
                        WRITEENABLE <= 1;  // Writing pulse on
                      end

        // Sub
        8'b0000_0011: begin
                        $display("Sub");
                        subMuxSelect <= 1; // Select the 2's complement value
                        immMuxSelect <= 1; // Select register value
                        ALUOP <= 1;        // ALU ADD 
                        WRITEENABLE <= 1;  // Writing pulse on
                      end


        // AND
        8'b0000_0100: begin
                        $display("AND");
                        subMuxSelect <= 0; // Select the original register 2 value
                        immMuxSelect <= 1; // Select register value
                        ALUOP <= 2;        // ALU AND 
                        WRITEENABLE <= 1;  // Writing pulse on
                      end

        // OR
        8'b0000_0101: begin
                        $display("OR");
                        subMuxSelect <= 1; // Select the original register 2 value
                        immMuxSelect <= 1; // Select register value
                        ALUOP <= 3;        // ALU OR 
                        WRITEENABLE <= 1;  // Writing pulse on
                      end

        // JUMP
        8'b0000_0110: begin
                        $display("JUMP"); 
                        JUMP = 1;          // Select the jump address as the PC
                      end

        // BEQ
        8'b0000_0111: begin
                        $display("BEQ"); 
                        BRANCH <= 1;       // Select the branch address as the PC
                        subMuxSelect <= 1; // Select the 2's complement value
                        immMuxSelect <= 1; // Select register value
                        ALUOP <= 1;        // ALU ADD 
                      end
      endcase      

      #6 WRITEENABLE = 0; // Desable Writing

    end

    /* ------------------------------------------------------------------------------------------ */

endmodule

Group09_Lab05_Part4/cpu_tb.v
// Computer Architecture (CO224) - Lab 05
// Design: Testbench of Integrated CPU of Simple Processor
// Author: Isuru Nawinne
// Modified by: Janakantha S.M.B.G.
// Last Modified: 24/04/2024

`include "cpu.v"


module cpu_tb;

    reg CLK, RESET;
    wire [31:0] PC;
    reg [31:0] INSTRUCTION;
    
    /* 
    ------------------------
     SIMPLE INSTRUCTION MEM
    ------------------------
    */
    
    // TODO: Initialize an array of registers (8x1024) named 'instr_mem' to be used as instruction memory
    reg[7:0] instr_mem[1023:0];
    
    // TODO: Create combinational logic to support CPU instruction fetching, given the Program Counter(PC) value 
    //       (make sure you include the delay for instruction fetching here)
    always @ (PC)
    begin
        #2 
        INSTRUCTION[31:24] = instr_mem[PC+3];
        INSTRUCTION[23:16] = instr_mem[PC+2];
        INSTRUCTION[15:8]  = instr_mem[PC+1];
        INSTRUCTION[7:0]   = instr_mem[PC];
    end
    
    initial
    begin
        // Initialize instruction memory with the set of instructions you need execute on CPU
       /* 
        // METHOD 1: manually loading instructions to instr_mem 
        {instr_mem[3], instr_mem[2], instr_mem[1], instr_mem[0]}     = 32'b00000000_00000000_00000000_00000101; // loadi 0 0x05
        {instr_mem[7], instr_mem[6], instr_mem[5], instr_mem[4]}     = 32'b00000000_00000001_00000000_00001001; // loadi 1 0x09
        {instr_mem[11], instr_mem[10], instr_mem[9], instr_mem[8]}   = 32'b00000010_00000110_00000000_00000001; // add 6 0 1
        {instr_mem[15], instr_mem[14], instr_mem[13], instr_mem[12]} = 32'b00000001_00000000_00000000_00000110; // mov 0 6
        {instr_mem[19], instr_mem[18], instr_mem[17], instr_mem[16]} = 32'b00000000_00000001_00000000_00000001; // loadi 1 0x01
        {instr_mem[23], instr_mem[22], instr_mem[21], instr_mem[20]} = 32'b00000010_00000010_00000010_00000001; // add 2 2 1
        {instr_mem[27], instr_mem[26], instr_mem[25], instr_mem[24]} = 32'b00000110_00000011_00000000_00000000; // j 0x03
        // ------------------------------------- Empty two rows are here ------------------------------------------------ //
        {instr_mem[39], instr_mem[38], instr_mem[37], instr_mem[36]} = 32'b00000000_00000001_00000000_00000101; // loadi 1 0x05
        {instr_mem[43], instr_mem[42], instr_mem[41], instr_mem[40]} = 32'b00000000_00000010_00000000_00000001; // loadi 2 0x01
        {instr_mem[47], instr_mem[46], instr_mem[45], instr_mem[44]} = 32'b00000111_00000011_00000001_00000010; // beq 0x02 1 2*/
        
        // METHOD 2: loading instr_mem content from instr_mem.mem file
        $readmemb("instr_mem.mem", instr_mem);
    end
    
    /* 
    -----
     CPU
    -----
    */
    cpu mycpu(PC, INSTRUCTION, CLK, RESET);

    integer i;

    initial begin
        // generate files needed to plot the waveform using GTKWave
        $dumpfile("cpu_wavedata.vcd");
		$dumpvars(0, mycpu);
        
        for (i=0; i<8; i=i+1)
            $dumpvars(1, mycpu.regUnit.REGISTER[i]);
        
        RESET = 1'b0;
        CLK = 1'b0;
        
        // TODO: Reset the CPU (by giving a pulse to RESET signal) to start the program execution
        RESET = 1;
        #6
        RESET = 0;
        // finish simulation after some time
        #100
        $finish;
    end
    
    // clock signal generation
    always
        #4 CLK = ~CLK;
        

endmodule

Group09_Lab05_Part4/cpu_wavedata.vcd
$date
	Thu Jun 13 12:55:49 2024
$end
$version
	Icarus Verilog
$end
$timescale
	1s
$end
$scope module cpu_tb $end
$scope module mycpu $end
$var wire 1 ! CLK $end
$var wire 32 " INSTRUCTION [31:0] $end
$var wire 1 # RESET $end
$var wire 8 $ twos_Complemet [7:0] $end
$var wire 8 % subMuxOut [7:0] $end
$var wire 8 & pcAdderOut [7:0] $end
$var wire 8 ' jumpMuxOut [7:0] $end
$var wire 8 ( immMuxOut [7:0] $end
$var wire 8 ) branchMuxOut [7:0] $end
$var wire 1 * ZERO $end
$var wire 8 + REGOUT2 [7:0] $end
$var wire 8 , REGOUT1 [7:0] $end
$var wire 8 - ALURESULT [7:0] $end
$var reg 3 . ALUOP [2:0] $end
$var reg 1 / BRANCH $end
$var reg 8 0 IMMEDIATE1 [7:0] $end
$var reg 8 1 IMMEDIATE2 [7:0] $end
$var reg 1 2 JUMP $end
$var reg 8 3 OPCODE [7:0] $end
$var reg 32 4 PC [31:0] $end
$var reg 8 5 READREG1 [7:0] $end
$var reg 8 6 READREG2 [7:0] $end
$var reg 1 7 WRITEENABLE $end
$var reg 8 8 WRITEREG [7:0] $end
$var reg 1 9 immMuxSelect $end
$var reg 8 : nextPC [7:0] $end
$var reg 1 ; subMuxSelect $end
$scope module aluUnit $end
$var wire 3 < SELECT [2:0] $end
$var wire 8 = orOut [7:0] $end
$var wire 8 > fwdOut [7:0] $end
$var wire 8 ? andOut [7:0] $end
$var wire 8 @ addOut [7:0] $end
$var wire 8 A DATA2 [7:0] $end
$var wire 8 B DATA1 [7:0] $end
$var reg 8 C RESULT [7:0] $end
$var reg 1 * ZERO $end
$scope module addUnit $end
$var wire 8 D RESULT [7:0] $end
$var wire 8 E DATA2 [7:0] $end
$var wire 8 F DATA1 [7:0] $end
$upscope $end
$scope module andUnit $end
$var wire 8 G RESULT [7:0] $end
$var wire 8 H DATA2 [7:0] $end
$var wire 8 I DATA1 [7:0] $end
$upscope $end
$scope module fwdUnit $end
$var wire 8 J RESULT [7:0] $end
$var wire 8 K DATA2 [7:0] $end
$upscope $end
$scope module orUnit $end
$var wire 8 L RESULT [7:0] $end
$var wire 8 M DATA2 [7:0] $end
$var wire 8 N DATA1 [7:0] $end
$upscope $end
$upscope $end
$scope module branchMux $end
$var wire 8 O IN1 [7:0] $end
$var wire 1 P SELECT $end
$var wire 8 Q IN2 [7:0] $end
$var reg 8 R OUT [7:0] $end
$upscope $end
$scope module complementUnit $end
$var wire 8 S RESULT [7:0] $end
$var wire 8 T DATA2 [7:0] $end
$upscope $end
$scope module immediateMux $end
$var wire 8 U IN1 [7:0] $end
$var wire 1 9 SELECT $end
$var wire 8 V IN2 [7:0] $end
$var reg 8 W OUT [7:0] $end
$upscope $end
$scope module jumpMux $end
$var wire 8 X IN1 [7:0] $end
$var wire 1 2 SELECT $end
$var wire 8 Y IN2 [7:0] $end
$var reg 8 Z OUT [7:0] $end
$upscope $end
$scope module pcAdder $end
$var wire 8 [ DATA1 [7:0] $end
$var wire 8 \ DATA2 [7:0] $end
$var wire 8 ] RESULT [7:0] $end
$upscope $end
$scope module regUnit $end
$var wire 1 ! CLK $end
$var wire 8 ^ IN [7:0] $end
$var wire 8 _ INADDRESS [7:0] $end
$var wire 8 ` OUT1ADDRESS [7:0] $end
$var wire 8 a OUT2ADDRESS [7:0] $end
$var wire 1 # RESET $end
$var wire 1 7 WRITE $end
$var reg 8 b OUT1 [7:0] $end
$var reg 8 c OUT2 [7:0] $end
$var integer 32 d i [31:0] $end
$upscope $end
$scope module subMux $end
$var wire 8 e IN1 [7:0] $end
$var wire 8 f IN2 [7:0] $end
$var wire 1 ; SELECT $end
$var reg 8 g OUT [7:0] $end
$upscope $end
$upscope $end
$upscope $end
$scope module cpu_tb $end
$scope module mycpu $end
$scope module regUnit $end
$var reg 8 h \REGISTER[0] [7:0] $end
$upscope $end
$upscope $end
$upscope $end
$scope module cpu_tb $end
$scope module mycpu $end
$scope module regUnit $end
$var reg 8 i \REGISTER[1] [7:0] $end
$upscope $end
$upscope $end
$upscope $end
$scope module cpu_tb $end
$scope module mycpu $end
$scope module regUnit $end
$var reg 8 j \REGISTER[2] [7:0] $end
$upscope $end
$upscope $end
$upscope $end
$scope module cpu_tb $end
$scope module mycpu $end
$scope module regUnit $end
$var reg 8 k \REGISTER[3] [7:0] $end
$upscope $end
$upscope $end
$upscope $end
$scope module cpu_tb $end
$scope module mycpu $end
$scope module regUnit $end
$var reg 8 l \REGISTER[4] [7:0] $end
$upscope $end
$upscope $end
$upscope $end
$scope module cpu_tb $end
$scope module mycpu $end
$scope module regUnit $end
$var reg 8 m \REGISTER[5] [7:0] $end
$upscope $end
$upscope $end
$upscope $end
$scope module cpu_tb $end
$scope module mycpu $end
$scope module regUnit $end
$var reg 8 n \REGISTER[6] [7:0] $end
$upscope $end
$upscope $end
$upscope $end
$scope module cpu_tb $end
$scope module mycpu $end
$scope module regUnit $end
$var reg 8 o \REGISTER[7] [7:0] $end
$upscope $end
$upscope $end
$upscope $end
$enddefinitions $end
$comment Show the parameter values. $end
$dumpall
$end
#0
$dumpvars
bx o
bx n
bx m
bx l
bx k
bx j
bx i
bx h
bx g
bx f
bx e
bx d
bx c
bx b
bx a
bx `
bx _
bx ^
bx ]
bx00 \
bx [
bx Z
bx Y
bx X
bx W
bx V
bx U
bx T
bx S
bx R
bx Q
xP
bx O
bx N
bx M
bx L
bx K
bx J
bx I
bx H
bx G
bx F
bx E
bx D
bx C
bx B
bx A
bx @
bx ?
bx >
bx =
bx <
x;
bx :
x9
bx 8
x7
bx 6
bx 5
bx 4
bx 3
x2
bx 1
bx 0
x/
bx .
bx -
bx ,
bx +
x*
bx )
bx (
bx '
bx &
bx %
bx $
1#
bx "
0!
$end
#4
1!
#5
b0 :
b0 O
b0 [
b0 4
b0 o
b0 n
b0 m
b0 l
b0 k
b0 j
b0 i
b0 h
b1000 d
#6
b100 :
b100 O
b100 [
0#
#7
b0 \
b101 1
b101 U
b0 0
b101 6
b101 a
b0 5
b0 `
b0 8
b0 _
b0 3
b100 '
b100 Z
b100 )
b100 R
b100 X
0P
0/
02
b101 "
#8
0*
b101 (
b101 A
b101 E
b101 H
b101 K
b101 M
b101 W
17
b0 .
b0 <
09
0!
#9
b101 -
b101 C
b101 ^
bx1x1 =
bx1x1 L
b0x0x ?
b0x0x G
b101 >
b101 J
b100 &
b100 Q
b100 Y
b100 ]
b0 +
b0 T
b0 c
b0 e
b0 ,
b0 B
b0 F
b0 I
b0 N
b0 b
#10
b0 $
b0 S
b0 f
b101 =
b101 L
b0 ?
b0 G
#11
b101 @
b101 D
#12
1!
#13
b100 4
b101 h
#14
b1000 '
b1000 Z
b1000 )
b1000 R
b1000 X
b1000 :
b1000 O
b1000 [
07
#15
b1001 (
b1001 A
b1001 E
b1001 H
b1001 K
b1001 M
b1001 W
b100 \
b1001 1
b1001 U
b1 0
b1001 6
b1001 a
b1 8
b1 _
b10000000000001001 "
#16
17
b1001 -
b1001 C
b1001 ^
b1001 =
b1001 L
b1001 >
b1001 J
0!
#17
b1001 @
b1001 D
b1100 &
b1100 Q
b1100 Y
b1100 ]
b101 ,
b101 B
b101 F
b101 I
b101 N
b101 b
#18
b1101 =
b1101 L
b1 ?
b1 G
#19
b1110 @
b1110 D
#20
1!
#21
b1001 i
b1000 4
#22
b1100 '
b1100 Z
b1100 )
b1100 R
b1100 X
b1100 :
b1100 O
b1100 [
07
#23
b1 (
b1 A
b1 E
b1 H
b1 K
b1 M
b1 W
b11000 \
b1 1
b1 U
b110 0
b1 6
b1 a
b110 8
b110 _
b10 3
b10000001100000000000000001 "
#24
b0 (
b0 A
b0 E
b0 H
b0 K
b0 M
b0 W
b0 %
b0 V
b0 g
17
b1 .
b1 <
19
0;
b1110 -
b1110 C
b1110 ^
b101 =
b101 L
b1 >
b1 J
0!
#25
b1001 (
b1001 A
b1001 E
b1001 H
b1001 K
b1001 M
b1001 W
b1001 %
b1001 V
b1001 g
b0 ?
b0 G
b0 >
b0 J
b100100 &
b100100 Q
b100100 Y
b100100 ]
b1001 +
b1001 T
b1001 c
b1001 e
#26
b1101 =
b1101 L
b1 ?
b1 G
b1001 >
b1001 J
b11110111 $
b11110111 S
b11110111 f
#28
1!
#29
b1100 4
b1110 n
#30
b10000 '
b10000 Z
b10000 )
b10000 R
b10000 X
b10000 :
b10000 O
b10000 [
07
#31
bx00 \
bx 1
bx U
bx 0
bx 6
bx a
bx 5
bx `
bx 8
bx _
bx 3
bx "
#32
0!
#33
bx (
bx A
bx E
bx H
bx K
bx M
bx W
bx %
bx V
bx g
bx &
bx Q
bx Y
bx ]
bx +
bx T
bx c
bx e
bx ,
bx B
bx F
bx I
bx N
bx b
#34
bx >
bx J
bx $
bx S
bx f
bx =
bx L
bx ?
bx G
#35
bx -
bx C
bx ^
bx @
bx D
#36
1!
#37
b10000 4
#38
b10100 '
b10100 Z
b10100 )
b10100 R
b10100 X
b10100 :
b10100 O
b10100 [
#40
0!
#44
1!
#45
b10100 4
#46
b11000 '
b11000 Z
b11000 )
b11000 R
b11000 X
b11000 :
b11000 O
b11000 [
#48
0!
#52
1!
#53
b11000 4
#54
b11100 '
b11100 Z
b11100 )
b11100 R
b11100 X
b11100 :
b11100 O
b11100 [
#56
0!
#60
1!
#61
b11100 4
#62
b100000 '
b100000 Z
b100000 )
b100000 R
b100000 X
b100000 :
b100000 O
b100000 [
#64
0!
#68
1!
#69
b100000 4
#70
b100100 '
b100100 Z
b100100 )
b100100 R
b100100 X
b100100 :
b100100 O
b100100 [
#72
0!
#76
1!
#77
b100100 4
#78
b101000 '
b101000 Z
b101000 )
b101000 R
b101000 X
b101000 :
b101000 O
b101000 [
#80
0!
#84
1!
#85
b101000 4
#86
b101100 '
b101100 Z
b101100 )
b101100 R
b101100 X
b101100 :
b101100 O
b101100 [
#88
0!
#92
1!
#93
b101100 4
#94
b110000 '
b110000 Z
b110000 )
b110000 R
b110000 X
b110000 :
b110000 O
b110000 [
#96
0!
#100
1!
#101
b110000 4
#102
b110100 '
b110100 Z
b110100 )
b110100 R
b110100 X
b110100 :
b110100 O
b110100 [
