Group09_Lab05_Part2/reg_file.v
/*
    * CO224 - Computer Architecture
    * Lab 05 - Part 2
    * reg_file module
    * Group 09 (E/20/148, E/20/157)
    * 2024-04-09
    * Version 1.0
*/

module reg_file(IN, OUT1, OUT2, INADDRESS, OUT1ADDRESS, OUT2ADDRESS, WRITE, CLK, RESET);
    // Port declaration
    input [7:0] IN; // Data input for writing
    input [2:0] INADDRESS, OUT1ADDRESS, OUT2ADDRESS; // Data addresses

    input CLK, RESET, WRITE; // Control signals

    output [7:0] OUT1, OUT2; // Data outputs

    // Register Allocation
    reg [7:0] REGISTER [7:0]; // 8 x 8 register block

    // variable for counting
    integer i;

    // Asynchronous Data Operations (READ)
    // Artificial delay of 2 time units
    //if (WRITE == 1'b0) begin
      //$display("READ DATA");
      assign #2 OUT1 = REGISTER[OUT1ADDRESS];
      assign #2 OUT2 = REGISTER[OUT2ADDRESS];
    //end

    // Synchronous Data Operations (WRITE, RESET)
    always @ (posedge CLK)
    begin
      // RESET (Highest Priority Operation)
      if (RESET == 1'b1) begin
        $display("RESET MEMORY");
        #1 for(i=0; i<8; i = i+1) begin
          REGISTER[i] = 8'b0000_0000;
        end
      end

      // WRITE
      else if (WRITE == 1'b1) begin
        $display("WRITE DATA");
        #1 REGISTER[INADDRESS] = IN; // Writing data to the given register
      end
    end

endmodule

Group09_Lab05_Part2/Testbench.v
/*
    * CO224 - Computer Architecture
    * Lab 05 - Part 2
    * Testbench
    * Group 09 (E/20/148, E/20/157)
    * 2024-04-09
    * Version 1.0
*/

// Import files
`include "reg_file.v"

module Testbench;
    // Defining registers
    reg [7:0] WRITEDATA;
    reg [2:0] READREG1, READREG2, WRITEREG;

    // Difining nets
    wire [7:0] REGOUT1, REGOUT2;
    reg CLOCK, RESET, WRITEENABLE;

    //Instantiating the register file within the testbench module
	reg_file myReg(WRITEDATA, REGOUT1, REGOUT2, WRITEREG, READREG1, READREG2, WRITEENABLE, CLOCK, RESET);

    // Simulation
    initial begin
      $dumpfile("Testbench.vcd");
	  $dumpvars(0, myReg);
      
      // Initial Conditions
      WRITEENABLE = 0;
      RESET = 0;
      CLOCK = 0;  
      #2

      // Reset All
      RESET = 1;
      #2
      RESET = 0;

      // Write 7 to REG1
      WRITEREG = 1;    // Register number
      WRITEDATA = 7;   // Data
      WRITEENABLE = 1; // Write Enable pulse
      #2
      WRITEENABLE = 0; // Write Desable pulse
      #2               // Wait 2 time units


      // Read existing data
      READREG1 = 0;  // Data in REG0 dump into OUT1 
      READREG2 = 1;  // Data in REG1 dump into OUT2
      #5             // Wait 5 time units

      // Write 12 to REG6
      WRITEREG = 6;    // Register number
      WRITEDATA = 12;  // Data
      WRITEENABLE = 1; // Write Enable pulse
      #2
      WRITEENABLE = 0; // Write Desable pulse
      #3               // Wait 2 time units


      // Read existing data
      READREG1 = 6;  // Data in REG6 dump into OUT1 
      READREG2 = 1;  // Data in REG1 dump into OUT2
      #5             // Wait 5 time units

      // Write 7 to REG1
      WRITEREG = 1;    // Register number
      WRITEDATA = 7;   // Data
      /*WRITE is not enabled. So, output is not changing for next 5 time units.*/


      // Read existing data
      READREG1 = 6;  // Data in REG0 dump into OUT1 
      READREG2 = 1;  // Data in REG1 dump into OUT2
      #5             // Wait 5 time units


      $display("DONE!");
      $finish;
    end

    // CLOCK Pulse generator
    always #1 CLOCK = !CLOCK;

endmodule

Group09_Lab05_Part2/Testbench.vcd
$date
	Wed Apr 10 09:10:02 2024
$end
$version
	Icarus Verilog
$end
$timescale
	1s
$end
$scope module Testbench $end
$scope module myReg $end
$var wire 1 ! CLK $end
$var wire 8 " IN [7:0] $end
$var wire 3 # INADDRESS [2:0] $end
$var wire 8 $ OUT1 [7:0] $end
$var wire 3 % OUT1ADDRESS [2:0] $end
$var wire 8 & OUT2 [7:0] $end
$var wire 3 ' OUT2ADDRESS [2:0] $end
$var wire 1 ( RESET $end
$var wire 1 ) WRITE $end
$var integer 32 * i [31:0] $end
$upscope $end
$upscope $end
$enddefinitions $end
$comment Show the parameter values. $end
$dumpall
$end
#0
$dumpvars
bx *
0)
0(
bx '
bx &
bx %
bx $
bx #
bx "
0!
$end
#1
1!
#2
0!
1(
#3
1!
#4
b1000 *
0!
1)
b111 "
b1 #
0(
#5
1!
#6
0!
0)
#7
1!
#8
0!
b1 '
b0 %
#9
1!
#10
0!
b111 &
b0 $
#11
1!
#12
0!
#13
1!
1)
b1100 "
b110 #
#14
0!
#15
1!
0)
#16
0!
#17
1!
#18
0!
b110 %
#19
1!
#20
0!
b1100 $
#21
1!
#22
0!
#23
1!
b111 "
b1 #
